sema4ai/action_server/__init__.py
sema4ai/action_server/__main__.py
sema4ai/action_server/_action_package_handler.py
sema4ai/action_server/_actions_cloud.py
sema4ai/action_server/_actions_import.py
sema4ai/action_server/_actions_process_pool.py
sema4ai/action_server/_actions_run.py
sema4ai/action_server/_actions_run_helpers.py
sema4ai/action_server/_api_action_package.py
sema4ai/action_server/_api_action_routes.py
sema4ai/action_server/_api_oauth2.py
sema4ai/action_server/_api_run.py
sema4ai/action_server/_api_secrets.py
sema4ai/action_server/_app.py
sema4ai/action_server/_ask_user.py
sema4ai/action_server/_cli_helpers.py
sema4ai/action_server/_cli_impl.py
sema4ai/action_server/_database.py
sema4ai/action_server/_datadir_commands.py
sema4ai/action_server/_devenv.py
sema4ai/action_server/_download_rcc.py
sema4ai/action_server/_encryption.py
sema4ai/action_server/_errors.py
sema4ai/action_server/_errors_action_server.py
sema4ai/action_server/_gen_ids.py
sema4ai/action_server/_models.py
sema4ai/action_server/_new_project.py
sema4ai/action_server/_new_project_helpers.py
sema4ai/action_server/_oauth2.py
sema4ai/action_server/_preload_actions/__init__.py
sema4ai/action_server/_preload_actions/preload_actions.py
sema4ai/action_server/_preload_actions/preload_actions_autoexit.py
sema4ai/action_server/_preload_actions/preload_actions_server_main.py
sema4ai/action_server/_preload_actions/preload_actions_streams.py
sema4ai/action_server/_preload_actions/preload_actions_teardown.py
sema4ai/action_server/_protocols.py
sema4ai/action_server/_rcc.py
sema4ai/action_server/_robo_utils/auth.py
sema4ai/action_server/_robo_utils/callback.py
sema4ai/action_server/_robo_utils/constants.py
sema4ai/action_server/_robo_utils/log_custom_handler.py
sema4ai/action_server/_robo_utils/log_formatter.py
sema4ai/action_server/_robo_utils/process.py
sema4ai/action_server/_robo_utils/run_in_thread.py
sema4ai/action_server/_robo_utils/system_mutex.py
sema4ai/action_server/_runs_state_cache.py
sema4ai_action_server-2.17.1.dist-info/entry_points.txt
sema4ai_action_server-2.17.1.dist-info/METADATA
sema4ai_action_server-2.17.1.dist-info/WHEEL
sema4ai_action_server-2.17.1.dist-info/RECORD
