Metadata-Version: 2.4
Name: sema4ai-action-server
Version: 2.17.1
Summary: Sema4AI Action Server
License: Apache-2.0
Author: Sema4.ai, Inc.
Author-email: dev@sema4.ai
Requires-Python: >=3.12,<3.14
Classifier: License :: OSI Approved :: Apache Software License
Classifier: Programming Language :: Python :: 3
Classifier: Programming Language :: Python :: 3.12
Classifier: Programming Language :: Python :: 3.13
Requires-Dist: aiohttp (>=3.13.2,<4.0.0)
Requires-Dist: cryptography (>=46.0.3,<47.0.0)
Requires-Dist: fastapi-slim (>=0.121.1,<0.122.0)
Requires-Dist: jsonschema (>=4.23.0,<5.0.0)
Requires-Dist: jsonschema-specifications (>=2024.10.1,<2025.0.0)
Requires-Dist: mcp (>=1.21.0,<2.0.0)
Requires-Dist: msgspec (>=0.19,<0.20)
Requires-Dist: psutil (>=5.0,<8.0)
Requires-Dist: pydantic (>=2.12.4,<3.0.0)
Requires-Dist: pyyaml (>=6.0.3,<7.0.0)
Requires-Dist: requests (>=2,<3)
Requires-Dist: requests_oauthlib (>=2.0,<3.0)
Requires-Dist: sema4ai-actions (>=1.6.4,<2.0.0)
Requires-Dist: sema4ai-common (>=0.2.1,<0.3.0)
Requires-Dist: termcolor (>=3.2.0,<4.0.0)
Requires-Dist: uvicorn (>=0.38.0,<0.39.0)
Requires-Dist: watchfiles (>=1.1.1,<2.0.0)
Requires-Dist: websockets (>=15.0.1,<16.0.0)
Project-URL: Homepage, https://github.com/sema4ai/actions/
Project-URL: Repository, https://github.com/sema4ai/actions/
